setup.py
OlymLibrary/OlymKeywords.py
OlymLibrary/RequestsKeywords.py
OlymLibrary/__init__.py
OlymLibrary/olymkeywords.py
OlymLibrary/version.py
OlymLibrary.egg-info/PKG-INFO
OlymLibrary.egg-info/SOURCES.txt
OlymLibrary.egg-info/dependency_links.txt
OlymLibrary.egg-info/requires.txt
OlymLibrary.egg-info/top_level.txt