Metadata-Version: 1.0
Name: OlymLibrary
Version: 0.7.12
Summary: olymtech test
Home-page: UNKNOWN
Author: zy
Author-email: 84497503@qq.com
License: MIT License
Keywords: OlymLibrary,robot
Platform: any
